{
    "type": "witness",
    "id": 47906,
    "is_unobserved": false,
    "is_excerpt": false,
    "siglum": "H7",
    "alternative_sigla": [],
    "status": "fragmentary",
    "creation_date_min": "1316-01-01",
    "creation_date_max": "1385-12-31",
    "creation_date_certainty": "2. Probable (33%-66%)",
    "creation_date_text": "'XIVm'",
    "urls": [
        "https://www.handschriftencensus.de/20269"
    ],
    "scripta": {
        "id": 46305,
        "name": "Vlaams",
        "description": "Dialect of Flanders.",
        "urls": []
    },
    "manuscripts": [
        {
            "id": 47904,
            "shelfmark": "Ltk. 211",
            "old_shelfmarks": [],
            "is_hypothetical": false,
            "collection_of_fragments": "No",
            "urls": [
                "https://www.handschriftencensus.de/20269"
            ],
            "witness_parts": [
                {
                    "id": 47907,
                    "part_order": 1,
                    "number_of_verses": 354,
                    "number_of_lines": 354,
                    "verses_per_line": "one verse per line",
                    "lines_are_incomplete": "Yes",
                    "page_ranges": [
                        "1r-1v",
                        "2r-2v"
                    ],
                    "has_initials": false,
                    "has_rubrication": false,
                    "has_incomplete_decoration": false,
                    "has_no_decoration": false,
                    "has_pictorial_designs": false,
                    "decoration_is_unknown": false
                }
            ],
            "repository": {
                "id": 43873,
                "name": "Universitaire Bibliotheken Leiden",
                "alternative_names": [
                    "Rijksuniversiteit te Leiden., Bibliotheek",
                    "Leiden University Library",
                    "Bibliotheek der Rijksuniversiteit Leiden",
                    "Universiteitsbibliotheek (Lejda).",
                    "Universiteitsbibliotheek (Leyde, Pays-Bas)",
                    "Rijksuniversiteit Leiden Bibliotheek"
                ],
                "viaf": "133132602.000000",
                "isni": "0000000122932800",
                "settlement": {
                    "id": 43362,
                    "name": "Leiden",
                    "region": "South Holland",
                    "country": "Netherlands",
                    "location_mappable": "POINT(4.49306 52.15833)",
                    "geonames_id": 2751773
                }
            }
        }
    ]
}